{
  "project_info": {
    "project_number": "258386485373",
    "firebase_url": "https://sbeepay.firebaseio.com",
    "project_id": "sbeepay",
    "storage_bucket": "sbeepay.appspot.com"
  },
  "client": [
    {
      "client_info": {
        "mobilesdk_app_id": "1:258386485373:android:ea5e4932c8383093f09114",
        "android_client_info": {
          "package_name": "com.stanleylab97.sbeepay"
        }
      },
      "oauth_client": [
        {
          "client_id": "258386485373-2olmkctguije8u18t2cjkgq37g8vu2rt.apps.googleusercontent.com",
          "client_type": 1,
          "android_info": {
            "package_name": "com.stanleylab97.sbeepay",
            "certificate_hash": "b37afbd725cabf53379f6adac1dbf0b5709aa22f"
          }
        },
        {
          "client_id": "258386485373-k9pgb6dh504sem99bkb1i6opl1iae69d.apps.googleusercontent.com",
          "client_type": 3
        }
      ],
      "api_key": [
        {
          "current_key": "AIzaSyCSciIVCi0hm7HPpnvm4kaTMjoAhhDfw0g"
        }
      ],
      "services": {
        "appinvite_service": {
          "other_platform_oauth_client": [
            {
              "client_id": "258386485373-k9pgb6dh504sem99bkb1i6opl1iae69d.apps.googleusercontent.com",
              "client_type": 3
            }
          ]
        }
      }
    }
  ],
  "configuration_version": "1"
}